CHANGES.txt
MANIFEST.in
README.txt
VERSION.txt
setup.py
scripts/sshplaces
sshplaces/CHANGES.txt
sshplaces/LICENSE.txt
sshplaces/README.txt
sshplaces/__init__.py
sshplaces/__main__.py
sshplaces/servers.yaml
sshplaces/sshplaces.py
sshplaces/version.py
sshplaces.egg-info/PKG-INFO
sshplaces.egg-info/SOURCES.txt
sshplaces.egg-info/dependency_links.txt
sshplaces.egg-info/requires.txt
sshplaces.egg-info/top_level.txt
sshplaces/classes/Config.py
sshplaces/classes/Process.py
sshplaces/classes/README.txt
sshplaces/classes/__init__.py