Metadata-Version: 1.0
Name: sshplaces
Version: 0.1.15
Summary: A curses menu of ssh places.
Home-page: http://pypi.python.org/pypi/sshplaces/
Author: Steven hk Wong
Author-email: steven@wongsrus.net
License: GNU GENERAL PUBLIC LICENSE
Platform: UNKNOWN
